{
    "adminOrganizationList.organizations": "Organizations",
    "adminOrganizationList.geographicZone": "Geographic zone",
    "adminOrganizationList.noOrganizations": "No organizations found.",
    "adminOrganizationList.name": "Organization name",
    "adminOrganizationList.code": "Code",
    "adminOrganizationList.type": "Type",
    "adminOrganizationList.active": "Active",
    "adminOrganizationList.enabled": "Enabled",
    "adminOrganizationList.actions": "Actions",
    "adminOrganizationList.search": "Search",
    "adminOrganizationList.addOrganization": "Add Organization",
    "adminOrganizationList.edit": "Edit"
}
